[
  {
    "host": "175.45.176.71",
    "ptr": "",
    "date": "2015-09-26",
    "status": [
      "Up",
      "Up"
    ]
  },
  {
    "host": "175.45.176.79",
    "ptr": "",
    "date": "2015-09-26",
    "status": [
      "Up",
      "Up"
    ]
  },
  {
    "host": "175.45.178.142",
    "ptr": "",
    "date": "2015-09-26",
    "status": [
      "Up"
    ],
    "ports": [
      {
        "ipv4": 22,
        "fingerprint": "22/open/tcp//ssh//Cisco SSH 1.25 (protocol 1.99)/"
      },
      {
        "ipv4": 23,
        "fingerprint": "23/open/tcp//telnet//Cisco router telnetd/"
      }
    ],
    "ignored state": [
      "closed (998)"
    ]
  },
  {
    "host": "175.45.178.179",
    "ptr": "",
    "date": "2015-09-26",
    "status": [
      "Up"
    ],
    "ports": [
      {
        "ipv4": 22,
        "fingerprint": "22/open/tcp//ssh//OpenSSH 5.3 (protocol 2.0)/"
      },
      {
        "ipv4": 80,
        "fingerprint": "80/open/tcp//http//Apache httpd 2.2.15 ((Red Hat))/"
      },
      {
        "ipv4": 3211,
        "fingerprint": "3211/filtered/tcp//avsecuremgmt///"
      },
      {
        "ipv4": 6000,
        "fingerprint": "6000/open/tcp//X11//(access denied)/"
      },
      {
        "ipv4": 32775,
        "fingerprint": "32775/filtered/tcp//sometimes-rpc13///"
      },
      {
        "ipv4": 61900,
        "fingerprint": "61900/filtered/tcp//unknown///"
      }
    ],
    "ignored state": [
      "closed (994)"
    ]
  },
  {
    "host": "175.45.178.180",
    "ptr": "",
    "date": "2015-09-26",
    "status": [
      "Up"
    ],
    "ports": [
      {
        "ipv4": 22,
        "fingerprint": "22/open/tcp//ssh//OpenSSH 5.3 (protocol 2.0)/"
      },
      {
        "ipv4": 80,
        "fingerprint": "80/open/tcp//http//Apache httpd 2.2.15 ((Red Hat))/"
      },
      {
        "ipv4": 135,
        "fingerprint": "135/filtered/tcp//msrpc///"
      },
      {
        "ipv4": 139,
        "fingerprint": "139/filtered/tcp//netbios-ssn///"
      },
      {
        "ipv4": 445,
        "fingerprint": "445/filtered/tcp//microsoft-ds///"
      },
      {
        "ipv4": 545,
        "fingerprint": "545/filtered/tcp//ekshell///"
      },
      {
        "ipv4": 593,
        "fingerprint": "593/filtered/tcp//http-rpc-epmap///"
      },
      {
        "ipv4": 3784,
        "fingerprint": "3784/filtered/tcp//bfd-control///"
      },
      {
        "ipv4": 4443,
        "fingerprint": "4443/filtered/tcp//pharos///"
      },
      {
        "ipv4": 4444,
        "fingerprint": "4444/filtered/tcp//krb524///"
      },
      {
        "ipv4": 4567,
        "fingerprint": "4567/filtered/tcp//tram///"
      },
      {
        "ipv4": 6000,
        "fingerprint": "6000/open/tcp//X11//(access denied)/"
      }
    ],
    "ignored state": [
      "closed (988)"
    ]
  },
  {
    "host": "175.45.178.181",
    "ptr": "",
    "date": "2015-09-26",
    "status": [
      "Up"
    ],
    "ports": [
      {
        "ipv4": 22,
        "fingerprint": "22/open/tcp//ssh//OpenSSH 5.3 (protocol 2.0)/"
      },
      {
        "ipv4": 80,
        "fingerprint": "80/open/tcp//http//Apache httpd 2.2.15 ((Red Hat))/"
      },
      {
        "ipv4": 135,
        "fingerprint": "135/filtered/tcp//msrpc///"
      },
      {
        "ipv4": 139,
        "fingerprint": "139/filtered/tcp//netbios-ssn///"
      },
      {
        "ipv4": 445,
        "fingerprint": "445/filtered/tcp//microsoft-ds///"
      },
      {
        "ipv4": 593,
        "fingerprint": "593/filtered/tcp//http-rpc-epmap///"
      },
      {
        "ipv4": 801,
        "fingerprint": "801/filtered/tcp//device///"
      },
      {
        "ipv4": 1067,
        "fingerprint": "1067/filtered/tcp//instl_boots///"
      },
      {
        "ipv4": 1524,
        "fingerprint": "1524/filtered/tcp//ingreslock///"
      },
      {
        "ipv4": 1782,
        "fingerprint": "1782/filtered/tcp//hp-hcip///"
      },
      {
        "ipv4": 1935,
        "fingerprint": "1935/filtered/tcp//rtmp///"
      },
      {
        "ipv4": 2718,
        "fingerprint": "2718/filtered/tcp//pn-requester2///"
      },
      {
        "ipv4": 3269,
        "fingerprint": "3269/filtered/tcp//globalcatLDAPssl///"
      },
      {
        "ipv4": 3814,
        "fingerprint": "3814/filtered/tcp//neto-dcs///"
      },
      {
        "ipv4": 4444,
        "fingerprint": "4444/filtered/tcp//krb524///"
      },
      {
        "ipv4": 5060,
        "fingerprint": "5060/filtered/tcp//sip///"
      },
      {
        "ipv4": 5679,
        "fingerprint": "5679/filtered/tcp//activesync///"
      },
      {
        "ipv4": 6000,
        "fingerprint": "6000/open/tcp//X11//(access denied)/"
      },
      {
        "ipv4": 6646,
        "fingerprint": "6646/filtered/tcp//unknown///"
      },
      {
        "ipv4": 8022,
        "fingerprint": "8022/filtered/tcp//oa-system///"
      },
      {
        "ipv4": 9103,
        "fingerprint": "9103/filtered/tcp//jetdirect///"
      },
      {
        "ipv4": 27355,
        "fingerprint": "27355/filtered/tcp//unknown///"
      },
      {
        "ipv4": 33354,
        "fingerprint": "33354/filtered/tcp//unknown///"
      },
      {
        "ipv4": 49175,
        "fingerprint": "49175/filtered/tcp//unknown///"
      },
      {
        "ipv4": 50800,
        "fingerprint": "50800/filtered/tcp//unknown///"
      }
    ],
    "ignored state": [
      "closed (975)"
    ]
  },
  {
    "host": "175.45.178.182",
    "ptr": "",
    "date": "2015-09-26",
    "status": [
      "Up"
    ],
    "ports": [
      {
        "ipv4": 22,
        "fingerprint": "22/open/tcp//ssh//OpenSSH 5.3 (protocol 2.0)/"
      },
      {
        "ipv4": 80,
        "fingerprint": "80/open/tcp//http//Apache httpd 2.2.15 ((Red Hat))/"
      },
      {
        "ipv4": 135,
        "fingerprint": "135/filtered/tcp//msrpc///"
      },
      {
        "ipv4": 139,
        "fingerprint": "139/filtered/tcp//netbios-ssn///"
      },
      {
        "ipv4": 445,
        "fingerprint": "445/filtered/tcp//microsoft-ds///"
      },
      {
        "ipv4": 593,
        "fingerprint": "593/filtered/tcp//http-rpc-epmap///"
      },
      {
        "ipv4": 1782,
        "fingerprint": "1782/filtered/tcp//hp-hcip///"
      },
      {
        "ipv4": 1972,
        "fingerprint": "1972/filtered/tcp//intersys-cache///"
      },
      {
        "ipv4": 4444,
        "fingerprint": "4444/filtered/tcp//krb524///"
      },
      {
        "ipv4": 6000,
        "fingerprint": "6000/open/tcp//X11//(access denied)/"
      }
    ],
    "ignored state": [
      "closed (990)"
    ]
  },
  {
    "host": "175.45.178.183",
    "ptr": "",
    "date": "2015-09-26",
    "status": [
      "Up"
    ],
    "ports": [
      {
        "ipv4": 22,
        "fingerprint": "22/open/tcp//ssh//OpenSSH 5.3 (protocol 2.0)/"
      },
      {
        "ipv4": 80,
        "fingerprint": "80/open/tcp//http//Apache httpd 2.2.15 ((Red Hat))/"
      },
      {
        "ipv4": 135,
        "fingerprint": "135/filtered/tcp//msrpc///"
      },
      {
        "ipv4": 139,
        "fingerprint": "139/filtered/tcp//netbios-ssn///"
      },
      {
        "ipv4": 445,
        "fingerprint": "445/filtered/tcp//microsoft-ds///"
      },
      {
        "ipv4": 593,
        "fingerprint": "593/filtered/tcp//http-rpc-epmap///"
      },
      {
        "ipv4": 4444,
        "fingerprint": "4444/filtered/tcp//krb524///"
      },
      {
        "ipv4": 6000,
        "fingerprint": "6000/open/tcp//X11//(access denied)/"
      }
    ],
    "ignored state": [
      "closed (992)"
    ]
  },
  {
    "host": "175.45.178.184",
    "ptr": "",
    "date": "2015-09-26",
    "status": [
      "Up"
    ],
    "ports": [
      {
        "ipv4": 22,
        "fingerprint": "22/open/tcp//ssh//OpenSSH 5.3 (protocol 2.0)/"
      },
      {
        "ipv4": 80,
        "fingerprint": "80/open/tcp//http//Apache httpd 2.2.15 ((Red Hat))/"
      },
      {
        "ipv4": 135,
        "fingerprint": "135/filtered/tcp//msrpc///"
      },
      {
        "ipv4": 139,
        "fingerprint": "139/filtered/tcp//netbios-ssn///"
      },
      {
        "ipv4": 445,
        "fingerprint": "445/filtered/tcp//microsoft-ds///"
      },
      {
        "ipv4": 593,
        "fingerprint": "593/filtered/tcp//http-rpc-epmap///"
      },
      {
        "ipv4": 1058,
        "fingerprint": "1058/filtered/tcp//nim///"
      },
      {
        "ipv4": 1075,
        "fingerprint": "1075/filtered/tcp//rdrmshc///"
      },
      {
        "ipv4": 1213,
        "fingerprint": "1213/filtered/tcp//mpc-lifenet///"
      },
      {
        "ipv4": 1417,
        "fingerprint": "1417/filtered/tcp//timbuktu-srv1///"
      },
      {
        "ipv4": 3052,
        "fingerprint": "3052/filtered/tcp//powerchute///"
      },
      {
        "ipv4": 3546,
        "fingerprint": "3546/filtered/tcp//unknown///"
      },
      {
        "ipv4": 3878,
        "fingerprint": "3878/filtered/tcp//fotogcad///"
      },
      {
        "ipv4": 4003,
        "fingerprint": "4003/filtered/tcp//pxc-splr-ft///"
      },
      {
        "ipv4": 4444,
        "fingerprint": "4444/filtered/tcp//krb524///"
      },
      {
        "ipv4": 4446,
        "fingerprint": "4446/filtered/tcp//n1-fwp///"
      },
      {
        "ipv4": 5120,
        "fingerprint": "5120/filtered/tcp//unknown///"
      },
      {
        "ipv4": 5432,
        "fingerprint": "5432/filtered/tcp//postgresql///"
      },
      {
        "ipv4": 6000,
        "fingerprint": "6000/open/tcp//X11?///"
      },
      {
        "ipv4": 8007,
        "fingerprint": "8007/filtered/tcp//ajp12///"
      },
      {
        "ipv4": 9071,
        "fingerprint": "9071/filtered/tcp//unknown///"
      },
      {
        "ipv4": 9535,
        "fingerprint": "9535/filtered/tcp//man///"
      },
      {
        "ipv4": 16016,
        "fingerprint": "16016/filtered/tcp//unknown///"
      },
      {
        "ipv4": 23502,
        "fingerprint": "23502/filtered/tcp//unknown///"
      },
      {
        "ipv4": 34572,
        "fingerprint": "34572/filtered/tcp//unknown///"
      }
    ],
    "ignored state": [
      "closed (975)"
    ]
  },
  {
    "host": "175.45.178.185",
    "ptr": "",
    "date": "2015-09-26",
    "status": [
      "Up"
    ],
    "ports": [
      {
        "ipv4": 22,
        "fingerprint": "22/open/tcp//ssh//OpenSSH 5.3 (protocol 2.0)/"
      },
      {
        "ipv4": 80,
        "fingerprint": "80/open/tcp//http//Apache httpd 2.2.15 ((Red Hat))/"
      },
      {
        "ipv4": 85,
        "fingerprint": "85/filtered/tcp//mit-ml-dev///"
      },
      {
        "ipv4": 458,
        "fingerprint": "458/filtered/tcp//appleqtc///"
      },
      {
        "ipv4": 903,
        "fingerprint": "903/filtered/tcp//iss-console-mgr///"
      },
      {
        "ipv4": 1060,
        "fingerprint": "1060/filtered/tcp//polestar///"
      },
      {
        "ipv4": 1166,
        "fingerprint": "1166/filtered/tcp//qsm-remote///"
      },
      {
        "ipv4": 2381,
        "fingerprint": "2381/filtered/tcp//compaq-https///"
      },
      {
        "ipv4": 2383,
        "fingerprint": "2383/filtered/tcp//ms-olap4///"
      },
      {
        "ipv4": 5100,
        "fingerprint": "5100/filtered/tcp//admd///"
      },
      {
        "ipv4": 5280,
        "fingerprint": "5280/filtered/tcp//xmpp-bosh///"
      },
      {
        "ipv4": 6000,
        "fingerprint": "6000/open/tcp//X11//(access denied)/"
      },
      {
        "ipv4": 7402,
        "fingerprint": "7402/filtered/tcp//rtps-dd-mt///"
      },
      {
        "ipv4": 7920,
        "fingerprint": "7920/filtered/tcp//unknown///"
      },
      {
        "ipv4": 9878,
        "fingerprint": "9878/filtered/tcp//unknown///"
      }
    ],
    "ignored state": [
      "closed (985)"
    ]
  },
  {
    "host": "175.45.178.186",
    "ptr": "",
    "date": "2015-09-26",
    "status": [
      "Up"
    ],
    "ports": [
      {
        "ipv4": 22,
        "fingerprint": "22/open/tcp//ssh//OpenSSH 5.3 (protocol 2.0)/"
      },
      {
        "ipv4": 80,
        "fingerprint": "80/open/tcp//http//Apache httpd 2.2.15 ((Red Hat))/"
      },
      {
        "ipv4": 222,
        "fingerprint": "222/filtered/tcp//rsh-spx///"
      },
      {
        "ipv4": 593,
        "fingerprint": "593/filtered/tcp//http-rpc-epmap///"
      },
      {
        "ipv4": 1030,
        "fingerprint": "1030/filtered/tcp//iad1///"
      },
      {
        "ipv4": 1043,
        "fingerprint": "1043/filtered/tcp//boinc///"
      },
      {
        "ipv4": 1046,
        "fingerprint": "1046/filtered/tcp//wfremotertm///"
      },
      {
        "ipv4": 1074,
        "fingerprint": "1074/filtered/tcp//warmspotMgmt///"
      },
      {
        "ipv4": 1417,
        "fingerprint": "1417/filtered/tcp//timbuktu-srv1///"
      },
      {
        "ipv4": 1503,
        "fingerprint": "1503/filtered/tcp//imtc-mcs///"
      },
      {
        "ipv4": 2382,
        "fingerprint": "2382/filtered/tcp//ms-olap3///"
      },
      {
        "ipv4": 3052,
        "fingerprint": "3052/filtered/tcp//powerchute///"
      },
      {
        "ipv4": 3322,
        "fingerprint": "3322/filtered/tcp//active-net///"
      },
      {
        "ipv4": 4004,
        "fingerprint": "4004/filtered/tcp//pxc-roid///"
      },
      {
        "ipv4": 5120,
        "fingerprint": "5120/filtered/tcp//unknown///"
      },
      {
        "ipv4": 6000,
        "fingerprint": "6000/open/tcp//X11//(access denied)/"
      },
      {
        "ipv4": 7625,
        "fingerprint": "7625/filtered/tcp//unknown///"
      },
      {
        "ipv4": 34573,
        "fingerprint": "34573/filtered/tcp//unknown///"
      },
      {
        "ipv4": 41511,
        "fingerprint": "41511/filtered/tcp//unknown///"
      },
      {
        "ipv4": 42510,
        "fingerprint": "42510/filtered/tcp//caerpc///"
      },
      {
        "ipv4": 50002,
        "fingerprint": "50002/filtered/tcp//iiimsf///"
      }
    ],
    "ignored state": [
      "closed (979)"
    ]
  },
  {
    "host": "175.45.178.187",
    "ptr": "",
    "date": "2015-09-26",
    "status": [
      "Up"
    ],
    "ports": [
      {
        "ipv4": 20,
        "fingerprint": "20/filtered/tcp//ftp-data///"
      },
      {
        "ipv4": 22,
        "fingerprint": "22/open/tcp//ssh//OpenSSH 5.3 (protocol 2.0)/"
      },
      {
        "ipv4": 80,
        "fingerprint": "80/open/tcp//http//Apache httpd 2.2.15 ((Red Hat))/"
      },
      {
        "ipv4": 88,
        "fingerprint": "88/filtered/tcp//kerberos-sec///"
      },
      {
        "ipv4": 135,
        "fingerprint": "135/filtered/tcp//msrpc///"
      },
      {
        "ipv4": 139,
        "fingerprint": "139/filtered/tcp//netbios-ssn///"
      },
      {
        "ipv4": 445,
        "fingerprint": "445/filtered/tcp//microsoft-ds///"
      },
      {
        "ipv4": 555,
        "fingerprint": "555/filtered/tcp//dsf///"
      },
      {
        "ipv4": 593,
        "fingerprint": "593/filtered/tcp//http-rpc-epmap///"
      },
      {
        "ipv4": 625,
        "fingerprint": "625/filtered/tcp//apple-xsrvr-admin///"
      },
      {
        "ipv4": 3809,
        "fingerprint": "3809/filtered/tcp//apocd///"
      },
      {
        "ipv4": 4444,
        "fingerprint": "4444/filtered/tcp//krb524///"
      },
      {
        "ipv4": 5051,
        "fingerprint": "5051/filtered/tcp//ida-agent///"
      },
      {
        "ipv4": 5718,
        "fingerprint": "5718/filtered/tcp//dpm///"
      },
      {
        "ipv4": 6000,
        "fingerprint": "6000/open/tcp//X11//(access denied)/"
      },
      {
        "ipv4": 8008,
        "fingerprint": "8008/filtered/tcp//http///"
      },
      {
        "ipv4": 9111,
        "fingerprint": "9111/filtered/tcp//DragonIDSConsole///"
      },
      {
        "ipv4": 27000,
        "fingerprint": "27000/filtered/tcp//flexlm0///"
      },
      {
        "ipv4": 49160,
        "fingerprint": "49160/filtered/tcp//unknown///"
      },
      {
        "ipv4": 64623,
        "fingerprint": "64623/filtered/tcp//unknown///"
      },
      {
        "ipv4": 64680,
        "fingerprint": "64680/filtered/tcp//unknown///"
      }
    ],
    "ignored state": [
      "closed (979)"
    ]
  },
  {
    "host": "175.45.178.188",
    "ptr": "",
    "date": "2015-09-26",
    "status": [
      "Up"
    ],
    "ports": [
      {
        "ipv4": 22,
        "fingerprint": "22/open/tcp//ssh//OpenSSH 5.3 (protocol 2.0)/"
      },
      {
        "ipv4": 80,
        "fingerprint": "80/open/tcp//http//Apache httpd 2.2.15 ((Red Hat))/"
      },
      {
        "ipv4": 135,
        "fingerprint": "135/filtered/tcp//msrpc///"
      },
      {
        "ipv4": 139,
        "fingerprint": "139/filtered/tcp//netbios-ssn///"
      },
      {
        "ipv4": 445,
        "fingerprint": "445/filtered/tcp//microsoft-ds///"
      },
      {
        "ipv4": 548,
        "fingerprint": "548/filtered/tcp//afp///"
      },
      {
        "ipv4": 593,
        "fingerprint": "593/filtered/tcp//http-rpc-epmap///"
      },
      {
        "ipv4": 1105,
        "fingerprint": "1105/filtered/tcp//ftranhc///"
      },
      {
        "ipv4": 4444,
        "fingerprint": "4444/filtered/tcp//krb524///"
      },
      {
        "ipv4": 6000,
        "fingerprint": "6000/open/tcp//X11//(access denied)/"
      },
      {
        "ipv4": 16000,
        "fingerprint": "16000/filtered/tcp//fmsas///"
      }
    ],
    "ignored state": [
      "closed (989)"
    ]
  }
]